ponzischeme_game/__init__.py
ponzischeme_game/finance.py
ponzischeme_game/fundCard.py
ponzischeme_game/fundingBoard.py
ponzischeme_game/game.py
ponzischeme_game/log.py
ponzischeme_game/luxuryTile.py
ponzischeme_game/player.py
ponzischeme_game/status.py
ponzischeme_game/tradeOffer.py
ponzischeme_game-0.0.3.dist-info/LICENSE
ponzischeme_game-0.0.3.dist-info/METADATA
ponzischeme_game-0.0.3.dist-info/WHEEL
ponzischeme_game-0.0.3.dist-info/top_level.txt
ponzischeme_game-0.0.3.dist-info/RECORD
