Metadata-Version: 2.1
Name: ponzischeme-game
Version: 0.0.3
Summary: ponzischeme_game is a python package for handling the game state of the game Ponzi Scheme.
Home-page: https://github.com/peter-de-boer/ponzischeme_game
Author: Peter de Boer
Author-email: peterboer_private@hotmail.com
License: MIT
Platform: UNKNOWN
Classifier: Development Status :: 3 - Alpha
Classifier: License :: OSI Approved :: MIT License
Classifier: Programming Language :: Python
Classifier: Programming Language :: Python :: 3.6
Classifier: Programming Language :: Python :: 3.7
Classifier: Topic :: Software Development :: Libraries
Classifier: Topic :: Software Development :: Libraries :: Python Modules
Classifier: Intended Audience :: Developers
Requires-Python: >=3.6
